timedelta_iso8601/__init__.py
timedelta_iso8601-0.1.8.dist-info/LICENSE
timedelta_iso8601-0.1.8.dist-info/METADATA
timedelta_iso8601-0.1.8.dist-info/WHEEL
timedelta_iso8601-0.1.8.dist-info/top_level.txt
timedelta_iso8601-0.1.8.dist-info/RECORD
