Metadata-Version: 2.1
Name: timedelta-iso8601
Version: 0.1.8
Summary: Supplementary ISO8601 duration support for datetime.timedelta
Author: James Addison <jay@jp-hosting.net>
License: AGPL-3.0-or-later
Project-URL: Homepage, https://pypi.org/project/timedelta-iso8601/
Project-URL: Source, https://github.com/jayaddison/timedelta-iso8601.git/
Classifier: License :: OSI Approved :: GNU Affero General Public License v3 or later (AGPLv3+)
License-File: LICENSE
